{
  "experiment_id": "05-ooh-creative",
  "use_case": "restaurant",
  "cycles": 1,
  "parallel_execution": true,
  "elapsed_seconds": 0.01,
  "results": [
    {
      "variant": "baseline",
      "final_score": 18.428741498463037,
      "success": true,
      "error": null
    },
    {
      "variant": "urgency",
      "final_score": 20.146120324254476,
      "success": true,
      "error": null
    },
    {
      "variant": "social_proof",
      "final_score": 19.842221069425584,
      "success": true,
      "error": null
    },
    {
      "variant": "emotional",
      "final_score": 20.634761973776087,
      "success": true,
      "error": null
    }
  ],
  "best_variant": "emotional",
  "best_score": 20.634761973776087
}