{
  "experiment_id": "05-ooh-creative-social_proof",
  "config": {
    "experiment_id": "05-ooh-creative",
    "cycles": 1,
    "use_case": "restaurant",
    "parallel_variants": 4,
    "metrics": {
      "attention": {
        "weight": 0.25,
        "description": "Eye-catching and memorable"
      },
      "clarity": {
        "weight": 0.25,
        "description": "Clear message and call-to-action"
      },
      "relevance": {
        "weight": 0.25,
        "description": "Relevant to target audience"
      },
      "conversion_potential": {
        "weight": 0.25,
        "description": "Likelihood to drive action"
      }
    },
    "constraints": {
      "max_headline_length": 50,
      "max_body_length": 100,
      "style": "professional"
    }
  },
  "cycles_completed": 1,
  "results": [
    {
      "experiment_id": "05-ooh-creative-social_proof",
      "cycle": 1,
      "metrics": {
        "attention": 19.350657210774276,
        "clarity": 22.24064950668344,
        "relevance": 19.53472581607467,
        "conversion_potential": 22.758908217093094
      },
      "timestamp": "2026-03-18T00:56:13.398448",
      "metadata": {},
      "aggregate_score": 20.97123518765637
    }
  ]
}